vloc/__init__.py
vloc/__detect__/__detect__.py
vloc/__detect__/__info__.py
vloc/exception/__exception__.py
vloc/exception/__init__.py
vloc/module/__config__.py
vloc/module/__init__.py
vloc/module/__module__.py
vloc-0.1.17.dist-info/LICENSE.txt
vloc-0.1.17.dist-info/METADATA
vloc-0.1.17.dist-info/WHEEL
vloc-0.1.17.dist-info/top_level.txt
vloc-0.1.17.dist-info/RECORD
