Metadata-Version: 2.1
Name: vloc
Version: 0.1.17
Summary: An UI antomation tool based by YOLO
Author-email: Lin Yeh <lin_yeh@outlook.com>
License: MIT
Project-URL: GitHub, https://github.com/linyeh1129/vloc
Keywords: ui aumomation,computer vision
Classifier: Programming Language :: Python :: 3
Requires-Python: >=3.10
License-File: LICENSE.txt
Requires-Dist: opencv-python >=4.9.0.80
Requires-Dist: ultralytics >=8.1.1
Requires-Dist: pytesseract >=0.3.10
